nbconvert_inline_artifacts/__init__.py
nbconvert_inline_artifacts-1.0.dist-info/LICENSE
nbconvert_inline_artifacts-1.0.dist-info/METADATA
nbconvert_inline_artifacts-1.0.dist-info/WHEEL
nbconvert_inline_artifacts-1.0.dist-info/top_level.txt
nbconvert_inline_artifacts-1.0.dist-info/RECORD
