Metadata-Version: 2.1
Name: nbconvert-inline-artifacts
Version: 1.0
Summary: Augmentations to nbconvert to facilitate the incorporation of inline artifacts into web-able documents.
Home-page: https://github.com/hamelin/nbconvert-inline-artifacts
Author: Benoit Hamelin
Author-email: benoit@benoithamelin.com
Classifier: Development Status :: 3 - Alpha
Classifier: Intended Audience :: Developers
Classifier: License :: OSI Approved :: MIT License
Classifier: Programming Language :: Python :: 3
Classifier: Topic :: Software Development :: Interpreters
Requires-Python: >=3.7
License-File: LICENSE
Requires-Dist: nbconvert
